ruuvi_gateway_client/__init__.py
ruuvi_gateway_client/gateway.py
ruuvi_gateway_client/parser.py
ruuvi_gateway_client/types.py
ruuvi_gateway_client-0.1.0.dist-info/LICENSE
ruuvi_gateway_client-0.1.0.dist-info/METADATA
ruuvi_gateway_client-0.1.0.dist-info/WHEEL
ruuvi_gateway_client-0.1.0.dist-info/top_level.txt
ruuvi_gateway_client-0.1.0.dist-info/RECORD
