Metadata-Version: 2.1
Name: ruuvi-gateway-client
Version: 0.1.0
Summary: Client for Ruuvi Gateway
Home-page: https://github.com/ruuvi-friends/ruuvi-gateway-client
Author: Tomi Tuhkanen
Author-email: tomi.tuhkanen@iki.fi
Project-URL: Bug Tracker, https://github.com/ruuvi-friends/ruuvi-gateway-client/issues
Classifier: Programming Language :: Python :: 3
Classifier: License :: OSI Approved :: MIT License
Classifier: Operating System :: OS Independent
Classifier: Intended Audience :: Developers
Requires-Python: >=3.6
License-File: LICENSE
Requires-Dist: aiohttp
Requires-Dist: result
Requires-Dist: ruuvi-decoders
